metatags/__init__.py
metatags/admin.py
metatags/apps.py
metatags/forms.py
metatags/managers.py
metatags/models.py
metatags/receivers.py
metatags/tests.py
metatags/translation.py
metatags/utils.py
metatags/locale/ru/LC_MESSAGES/django.mo
metatags/locale/ru/LC_MESSAGES/django.po
metatags/locale/uk/LC_MESSAGES/django.mo
metatags/locale/uk/LC_MESSAGES/django.po
metatags/management/__init__.py
metatags/management/commands/__init__.py
metatags/management/commands/resetmetatagscache.py
metatags/migrations/0001_initial.py
metatags/migrations/0002_auto_20200209_1707.py
metatags/migrations/0003_auto_20200401_1917.py
metatags/migrations/__init__.py
metatags/static/metatags/css/metatags.css
metatags/templates/metatags/admin/edit_inline/stacked.html
metatags/templates/metatags/includes/metatags.html
metatags/templatetags/__init__.py
metatags/templatetags/meta_tags.py
metatags/templatetags/metatags.py
django_simple_metatags-2.0.3.dist-info/LICENSE.txt
django_simple_metatags-2.0.3.dist-info/METADATA
django_simple_metatags-2.0.3.dist-info/WHEEL
django_simple_metatags-2.0.3.dist-info/top_level.txt
django_simple_metatags-2.0.3.dist-info/RECORD
