Metadata-Version: 2.1
Name: django-simple-metatags
Version: 2.0.3
Summary: The django application allows to add title, keywords and description meta tags to site's pages.
Home-page: https://github.com/whitespy/django-simple-metatags
Author: Andrey Butenko
Author-email: whitespysoftware@gmail.com
License: UNKNOWN
Platform: any
Classifier: Environment :: Web Environment
Classifier: Intended Audience :: Developers
Classifier: Operating System :: OS Independent
Classifier: Programming Language :: Python
Classifier: Programming Language :: Python :: 3.6
Classifier: Programming Language :: Python :: 3.7
Classifier: Programming Language :: Python :: 3.8
Classifier: Programming Language :: Python :: 3.9
Classifier: Programming Language :: Python :: 3.10
Classifier: Framework :: Django
Classifier: Framework :: Django :: 2.1
Classifier: Framework :: Django :: 2.2
Classifier: Framework :: Django :: 3.0
Classifier: Framework :: Django :: 3.1
Classifier: Framework :: Django :: 3.2
License-File: LICENSE.txt
